{
    "result": {
        "status": {
            "msg": "", 
            "code": 0
        }, 
        "count": {
            "qreply": 2100, 
            "total": 2234, 
            "show": 36
        }, 
        "replydict": {
            "56838224-71E658A9-12F335AC7-868-8CB": [
                {
                    "status": "M_PASS", 
                    "nick": "帅且幽默", 
                    "thread": "", 
                    "parent": "", 
                    "level": "0", 
                    "ip": "171.220.17.8", 
                    "area": "四川成都", 
                    "mid": "5683406C-ABDC1108-8F7FB57C-868-86D", 
                    "against": "213", 
                    "vote": "0", 
                    "content": "说了实话就不用追究犯罪行为啦？", 
                    "usertype": "client", 
                    "length": "30", 
                    "rank": "0", 
                    "time": "2015-12-30 10:24:44", 
                    "newsid": "comos-fxmxxsr3989257", 
                    "config": "&from=palmnews&wb_verified=0&wb_screen_name=帅且幽默&wb_user_id=2407511420&wb_time=1451442284&wb_profile_img=http%3A%2F%2Ftp1.sinaimg.cn%2F2407511420%2F50%2F5728468872%2F1&area=四川成都", 
                    "agree": "213", 
                    "channel": "gn", 
                    "uid": "2407511420"
                }
            ], 
            "5683855D-DE597009-9CAFE23B-868-84F": [
                {
                    "status": "M_PASS", 
                    "nick": "帅且幽默", 
                    "thread": "", 
                    "parent": "", 
                    "level": "0", 
                    "ip": "171.220.17.8", 
                    "area": "四川成都", 
                    "mid": "5683406C-ABDC1108-8F7FB57C-868-86D", 
                    "against": "213", 
                    "vote": "0", 
                    "content": "说了实话就不用追究犯罪行为啦？", 
                    "usertype": "client", 
                    "length": "30", 
                    "rank": "0", 
                    "time": "2015-12-30 10:24:44", 
                    "newsid": "comos-fxmxxsr3989257", 
                    "config": "&from=palmnews&wb_verified=0&wb_screen_name=帅且幽默&wb_user_id=2407511420&wb_time=1451442284&wb_profile_img=http%3A%2F%2Ftp1.sinaimg.cn%2F2407511420%2F50%2F5728468872%2F1&area=四川成都", 
                    "agree": "213", 
                    "channel": "gn", 
                    "uid": "2407511420"
                }
            ], 
            "5683470A-E86CDE8-68ECA043-868-97D": [
                {
                    "status": "M_PASS", 
                    "nick": "biaopieany", 
                    "thread": "", 
                    "parent": "", 
                    "level": "0", 
                    "ip": "183.204.33.144", 
                    "area": "河南信阳", 
                    "mid": "568295CE-B7CC2190-132CC1769-868-91E", 
                    "against": "59", 
                    "vote": "0", 
                    "content": "出了这么多臭虫，以前怎么没发现？请解释。", 
                    "usertype": "wap", 
                    "length": "40", 
                    "rank": "0", 
                    "time": "2015-12-29 22:16:46", 
                    "newsid": "comos-fxmxxsr3989257", 
                    "config": "OS_TYPE=14&SOFT_TYPE=Build/KTU84P) Chrome/33.0.0.0 Safari/537.36&area=河南信阳&area=河南信阳", 
                    "agree": "59", 
                    "channel": "gn", 
                    "uid": "5147203433"
                }
            ], 
            "568346D5-E86CDE8-68ECA043-868-8CE": [
                {
                    "status": "M_PASS", 
                    "nick": "塔", 
                    "thread": "", 
                    "parent": "", 
                    "level": "0", 
                    "ip": "222.81.38.229", 
                    "area": "新疆石河子", 
                    "mid": "56829B03-DE5126E5-4FC0488E-868-799", 
                    "against": "78", 
                    "vote": "0", 
                    "content": "说了实话就没罪吗", 
                    "usertype": "wap", 
                    "length": "16", 
                    "rank": "0", 
                    "time": "2015-12-29 22:38:59", 
                    "newsid": "comos-fxmxxsr3989257", 
                    "config": "from=ucweb&OS_TYPE=14&SOFT_TYPE=Build/Che1-CL10) UCBrowser/10.8.5.689 U3/0.8.0 Safari/534.30&area=新疆石河子&area=新疆石河子", 
                    "agree": "78", 
                    "channel": "gn", 
                    "uid": "1338001550"
                }
            ]
        }, 
        "language": "ch", 
        "encoding": "gbk", 
        "top": [], 
        "cmntlist": [
            {
                "status": "M_PASS", 
                "nick": "frankcheung78", 
                "thread": "5683406C-ABDC1108-8F7FB57C-868-86D", 
                "parent": "5683406C-ABDC1108-8F7FB57C-868-86D", 
                "level": "1", 
                "ip": "222.89.112.9", 
                "area": "河南开封", 
                "mid": "5683855D-DE597009-9CAFE23B-868-84F", 
                "against": "0", 
                "vote": "0", 
                "content": "坦白从严，抗拒更严", 
                "usertype": "", 
                "length": "18", 
                "rank": "0", 
                "time": "2015-12-30 15:18:53", 
                "newsid": "comos-fxmxxsr3989257", 
                "config": "client_port=0&area=河南开封&wb_verified=0&wb_screen_name=frankcheung78&wb_user_id=2628772411&wb_time=1451459933&wb_profile_img=http%3A%2F%2Ftp4.sinaimg.cn%2F2628772411%2F50%2F5717381792%2F1&area=河南开封", 
                "agree": "0", 
                "channel": "gn", 
                "uid": "2628772411"
            }, 
            {
                "status": "M_PASS", 
                "nick": "用户3272644330", 
                "thread": "", 
                "parent": "", 
                "level": "0", 
                "ip": "124.235.201.70", 
                "area": "吉林长春", 
                "mid": "56838497-7CEBC946-C31096EA-868-921", 
                "against": "51", 
                "vote": "0", 
                "content": "是你，你珍惜么？", 
                "usertype": "", 
                "length": "16", 
                "rank": "0", 
                "time": "2015-12-30 15:15:34", 
                "newsid": "comos-fxmxxsr3989257", 
                "config": "client_port=0&area=吉林长春&wb_verified=0&wb_screen_name=ye85qing&wb_user_id=3272644330&wb_time=1451459735&wb_profile_img=http%3A%2F%2Ftp3.sinaimg.cn%2F3272644330%2F50%2F0%2F1&area=吉林长春", 
                "agree": "51", 
                "channel": "gn", 
                "uid": "3272644330"
            }, 
            {
                "status": "M_PASS", 
                "nick": "用户5086862023", 
                "thread": "5683406C-ABDC1108-8F7FB57C-868-86D", 
                "parent": "5683406C-ABDC1108-8F7FB57C-868-86D", 
                "level": "1", 
                "ip": "113.230.88.169", 
                "area": "辽宁抚顺", 
                "mid": "56838224-71E658A9-12F335AC7-868-8CB", 
                "against": "2", 
                "vote": "0", 
                "content": "强奸犯没有珍惜自首的机会，所以被判刑了！[嘻嘻]", 
                "usertype": "", 
                "length": "46", 
                "rank": "0", 
                "time": "2015-12-30 15:05:07", 
                "newsid": "comos-fxmxxsr3989257", 
                "config": "client_port=0&area=辽宁抚顺&wb_verified=0&wb_screen_name=山风10303&wb_user_id=5086862023&wb_time=1451459108&wb_profile_img=http%3A%2F%2Ftp4.sinaimg.cn%2F5086862023%2F50%2F22893484680%2F1&area=辽宁抚顺", 
                "agree": "2", 
                "channel": "gn", 
                "uid": "5086862023"
            }, 
            {
                "status": "M_PASS", 
                "nick": "糖宝宝85843", 
                "thread": "", 
                "parent": "", 
                "level": "0", 
                "ip": "211.139.70.84", 
                "area": "西藏拉萨", 
                "mid": "56837013-D38B4654-14231EC17-868-931", 
                "against": "1", 
                "vote": "0", 
                "content": "现在的媒体写的啥子，你知道吗，那应该连罪", 
                "usertype": "", 
                "length": "40", 
                "rank": "0", 
                "time": "2015-12-30 13:48:03", 
                "newsid": "comos-fxmxxsr3989257", 
                "config": "client_port=0&area=西藏拉萨&wb_verified=0&wb_screen_name=糖宝宝85843&wb_user_id=5405535255&wb_time=1451454483&wb_profile_img=http%3A%2F%2Ftp4.sinaimg.cn%2F5405535255%2F50%2F5715405464%2F1&area=西藏拉萨", 
                "agree": "1", 
                "channel": "gn", 
                "uid": "5405535255"
            }, 
            {
                "status": "M_PASS", 
                "nick": "指月愚僧", 
                "thread": "", 
                "parent": "", 
                "level": "0", 
                "ip": "119.145.142.147", 
                "area": "广东佛山", 
                "mid": "56836AEC-77918E93-9CF0001B-868-94B", 
                "against": "5", 
                "vote": "0", 
                "content": "这就是媒体的不厚道啦，人家凭什么交代，只要有一丝机会能不交代，都不能放过的。", 
                "usertype": "", 
                "length": "76", 
                "rank": "0", 
                "time": "2015-12-30 13:26:04", 
                "newsid": "comos-fxmxxsr3989257", 
                "config": "client_port=0&area=广东佛山&wb_verified=0&wb_screen_name=指月愚僧&wb_user_id=2632974363&wb_time=1451453164&wb_profile_img=http%3A%2F%2Ftp4.sinaimg.cn%2F2632974363%2F50%2F0%2F1&area=广东佛山", 
                "agree": "5", 
                "channel": "gn", 
                "uid": "2632974363"
            }, 
            {
                "status": "M_PASS", 
                "nick": "lyhgeomag", 
                "thread": "", 
                "parent": "", 
                "level": "0", 
                "ip": "218.247.1.1", 
                "area": "北京", 
                "mid": "56836A13-DAF70101-57144268-868-91A", 
                "against": "55", 
                "vote": "0", 
                "content": "aaa", 
                "usertype": "", 
                "length": "3", 
                "rank": "0", 
                "time": "2015-12-30 13:22:27", 
                "newsid": "comos-fxmxxsr3989257", 
                "config": "client_port=0&area=北京&area=北京", 
                "agree": "55", 
                "channel": "gn", 
                "uid": "1460945512"
            }, 
            {
                "status": "M_PASS", 
                "nick": "敌敌危", 
                "thread": "", 
                "parent": "", 
                "level": "0", 
                "ip": "14.152.68.210", 
                "area": "广东广州", 
                "mid": "568368C1-E9844D2-551D5556-868-8F4", 
                "against": "44", 
                "vote": "0", 
                "content": "“可杀不可辱”，共产党员么，绝不苟且偷生～～", 
                "usertype": "wap", 
                "length": "44", 
                "rank": "0", 
                "time": "2015-12-30 13:16:48", 
                "newsid": "comos-fxmxxsr3989257", 
                "config": "from=ucweb&OS_TYPE=13&SOFT_TYPE=UCBrowser/10.7.1.655&area=广东广州&wb_verified=0&wb_screen_name=敌敌危&wb_user_id=1427985750&wb_time=1451452609&wb_profile_img=http%3A%2F%2Ftp3.sinaimg.cn%2F1427985750%2F50%2F5608893412%2F1&area=广东广州", 
                "agree": "44", 
                "channel": "gn", 
                "uid": "1427985750"
            }, 
            {
                "status": "M_PASS", 
                "nick": "蓝色影子", 
                "thread": "", 
                "parent": "", 
                "level": "0", 
                "ip": "117.177.240.39", 
                "area": "四川内江", 
                "mid": "5683664C-75B1F027-4A6AD4C7-868-990", 
                "against": "34", 
                "vote": "0", 
                "content": "天啦,他要珍惜了是不是就官复原职?", 
                "usertype": "", 
                "length": "32", 
                "rank": "0", 
                "time": "2015-12-30 13:06:20", 
                "newsid": "comos-fxmxxsr3989257", 
                "config": "client_port=0&area=四川内江&wb_verified=0&wb_screen_name=蓝色影子w&wb_user_id=1248515271&wb_time=1451451980&wb_profile_img=http%3A%2F%2Ftp4.sinaimg.cn%2F1248515271%2F50%2F0%2F1&area=四川内江", 
                "agree": "34", 
                "channel": "gn", 
                "uid": "1248515271"
            }, 
            {
                "status": "M_PASS", 
                "nick": "用户1856051407", 
                "thread": "", 
                "parent": "", 
                "level": "0", 
                "ip": "119.35.179.135", 
                "area": "广东广州", 
                "mid": "568360BF-7723B387-6EA118CF-868-867", 
                "against": "1", 
                "vote": "0", 
                "content": "坦白从严，扢拒从宽，记住白生。", 
                "usertype": "client", 
                "length": "30", 
                "rank": "0", 
                "time": "2015-12-30 12:42:38", 
                "newsid": "comos-fxmxxsr3989257", 
                "config": "client_ip=119.35.179.135&port=5372&from=palmnews&wb_verified=0&wb_screen_name=我们的舍友是个极品&wb_user_id=1856051407&wb_time=1451450559&wb_profile_img=http%3A%2F%2Ftp4.sinaimg.cn%2F1856051407%2F50%2F5598880220%2F1&area=广东广州", 
                "agree": "1", 
                "channel": "gn", 
                "uid": "1856051407"
            }, 
            {
                "status": "M_PASS", 
                "nick": "jinjian819", 
                "thread": "", 
                "parent": "", 
                "level": "0", 
                "ip": "114.225.122.177", 
                "area": "江苏无锡", 
                "mid": "56835347-72E17AB1-4C65336A-868-80E", 
                "against": "11", 
                "vote": "0", 
                "content": "万一把组织上不知道的事说漏嘴了，就麻烦了，所以打死也不说。", 
                "usertype": "", 
                "length": "58", 
                "rank": "0", 
                "time": "2015-12-30 11:45:10", 
                "newsid": "comos-fxmxxsr3989257", 
                "config": "client_port=0&area=江苏无锡&area=江苏无锡", 
                "agree": "11", 
                "channel": "gn", 
                "uid": "1281700714"
            }, 
            {
                "status": "M_PASS", 
                "nick": "淡泊明志", 
                "thread": "", 
                "parent": "", 
                "level": "0", 
                "ip": "118.72.71.114", 
                "area": "山西大同", 
                "mid": "56835103-76484772-9F182FB1-868-839", 
                "against": "19", 
                "vote": "0", 
                "content": "树倒猴孙散，墙倒众人推。", 
                "usertype": "", 
                "length": "24", 
                "rank": "0", 
                "time": "2015-12-30 11:35:30", 
                "newsid": "comos-fxmxxsr3989257", 
                "config": "client_port=0&area=山西大同&wb_verified=0&wb_screen_name=GM不是请客吃饭&wb_user_id=2669162417&wb_time=1451446531&wb_profile_img=http%3A%2F%2Ftp2.sinaimg.cn%2F2669162417%2F50%2F0%2F1&area=山西大同", 
                "agree": "19", 
                "channel": "gn", 
                "uid": "2669162417"
            }, 
            {
                "status": "M_PASS", 
                "nick": "用户5806208808", 
                "thread": "", 
                "parent": "", 
                "level": "0", 
                "ip": "218.87.161.178", 
                "area": "江西吉安", 
                "mid": "56834DF3-DA57A1B2-15A13B728-868-8F2", 
                "against": "169", 
                "vote": "0", 
                "content": "媒体咋啥都晓得，特别是在事后？！！！", 
                "usertype": "", 
                "length": "36", 
                "rank": "0", 
                "time": "2015-12-30 11:22:27", 
                "newsid": "comos-fxmxxsr3989257", 
                "config": "client_port=0&area=江西吉安&area=江西吉安", 
                "agree": "169", 
                "channel": "gn", 
                "uid": "5806208808"
            }, 
            {
                "status": "M_PASS", 
                "nick": "用户1909338723", 
                "thread": "", 
                "parent": "", 
                "level": "0", 
                "ip": "120.36.149.49", 
                "area": "福建厦门", 
                "mid": "56834D7E-78249531-71CE3263-868-83C", 
                "against": "78", 
                "vote": "0", 
                "content": "没办法！胜者王败者寇，顺应潮流", 
                "usertype": "", 
                "length": "30", 
                "rank": "0", 
                "time": "2015-12-30 11:20:30", 
                "newsid": "comos-fxmxxsr3989257", 
                "config": "client_port=0&area=福建厦门&wb_verified=0&wb_screen_name=微博云中鹏&wb_user_id=1909338723&wb_time=1451445630&wb_profile_img=http%3A%2F%2Ftp4.sinaimg.cn%2F1909338723%2F50%2F5606316287%2F1&area=福建厦门", 
                "agree": "78", 
                "channel": "gn", 
                "uid": "1909338723"
            }, 
            {
                "status": "M_PASS", 
                "nick": "愿如梁上燕_叹花不解言", 
                "thread": "568295CE-B7CC2190-132CC1769-868-91E", 
                "parent": "568295CE-B7CC2190-132CC1769-868-91E", 
                "level": "1", 
                "ip": "14.134.205.232", 
                "area": "宁夏固原", 
                "mid": "5683470A-E86CDE8-68ECA043-868-97D", 
                "against": "111", 
                "vote": "0", 
                "content": "装聋作哑，上梁不正下梁歪。", 
                "usertype": "", 
                "length": "26", 
                "rank": "0", 
                "time": "2015-12-30 10:52:57", 
                "newsid": "comos-fxmxxsr3989257", 
                "config": "client_port=0&area=宁夏固原&wb_verified=0&wb_screen_name=愿如梁上燕_叹花不解言&wb_user_id=1760337987&wb_time=1451443978&wb_profile_img=http%3A%2F%2Ftp4.sinaimg.cn%2F1760337987%2F50%2F5679964208%2F0&area=宁夏固原", 
                "agree": "111", 
                "channel": "gn", 
                "uid": "1760337987"
            }, 
            {
                "status": "M_PASS", 
                "nick": "妩媚没什么大不了的", 
                "thread": "", 
                "parent": "", 
                "level": "0", 
                "ip": "106.45.192.80", 
                "area": "宁夏吴忠", 
                "mid": "56834709-6A2DC050-139B5C02A-868-96D", 
                "against": "16", 
                "vote": "0", 
                "content": "太轻了！直接抓去枪毙，压在人民群众头顶上的蛀虫！何必惋惜！中国不差千里马！", 
                "usertype": "", 
                "length": "74", 
                "rank": "0", 
                "time": "2015-12-30 10:52:56", 
                "newsid": "comos-fxmxxsr3989257", 
                "config": "client_port=0&area=宁夏吴忠&wb_verified=0&wb_screen_name=妩媚没什么大不了的&wb_user_id=5263179818&wb_time=1451443977&wb_profile_img=http%3A%2F%2Ftp3.sinaimg.cn%2F5263179818%2F50%2F5703546401%2F1&area=宁夏吴忠", 
                "agree": "16", 
                "channel": "gn", 
                "uid": "5263179818"
            }, 
            {
                "status": "M_PASS", 
                "nick": "愿如梁上燕_叹花不解言", 
                "thread": "56829B03-DE5126E5-4FC0488E-868-799", 
                "parent": "56829B03-DE5126E5-4FC0488E-868-799", 
                "level": "1", 
                "ip": "14.134.205.232", 
                "area": "宁夏固原", 
                "mid": "568346D5-E86CDE8-68ECA043-868-8CE", 
                "against": "63", 
                "vote": "0", 
                "content": "至少是立功表现，减轻处罚。", 
                "usertype": "", 
                "length": "26", 
                "rank": "0", 
                "time": "2015-12-30 10:52:05", 
                "newsid": "comos-fxmxxsr3989257", 
                "config": "client_port=0&area=宁夏固原&wb_verified=0&wb_screen_name=愿如梁上燕_叹花不解言&wb_user_id=1760337987&wb_time=1451443925&wb_profile_img=http%3A%2F%2Ftp4.sinaimg.cn%2F1760337987%2F50%2F5679964208%2F0&area=宁夏固原", 
                "agree": "63", 
                "channel": "gn", 
                "uid": "1760337987"
            }, 
            {
                "status": "M_PASS", 
                "nick": "帅且幽默", 
                "thread": "", 
                "parent": "", 
                "level": "0", 
                "ip": "171.220.17.8", 
                "area": "四川成都", 
                "mid": "5683406C-ABDC1108-8F7FB57C-868-86D", 
                "against": "213", 
                "vote": "0", 
                "content": "说了实话就不用追究犯罪行为啦？", 
                "usertype": "client", 
                "length": "30", 
                "rank": "0", 
                "time": "2015-12-30 10:24:44", 
                "newsid": "comos-fxmxxsr3989257", 
                "config": "&from=palmnews&wb_verified=0&wb_screen_name=帅且幽默&wb_user_id=2407511420&wb_time=1451442284&wb_profile_img=http%3A%2F%2Ftp1.sinaimg.cn%2F2407511420%2F50%2F5728468872%2F1&area=四川成都", 
                "agree": "213", 
                "channel": "gn", 
                "uid": "2407511420"
            }, 
            {
                "status": "M_PASS", 
                "nick": "myu_boat", 
                "thread": "", 
                "parent": "", 
                "level": "0", 
                "ip": "124.65.231.110", 
                "area": "北京", 
                "mid": "56833C6F-7C41E76E-53F6A74B-868-903", 
                "against": "88", 
                "vote": "0", 
                "content": "交待了就没事了？", 
                "usertype": "", 
                "length": "16", 
                "rank": "0", 
                "time": "2015-12-30 10:07:43", 
                "newsid": "comos-fxmxxsr3989257", 
                "config": "client_port=0&area=北京&wb_verified=0&wb_screen_name=HippoMango&wb_user_id=1408673611&wb_time=1451441263&wb_profile_img=http%3A%2F%2Ftp4.sinaimg.cn%2F1408673611%2F50%2F0%2F1&area=北京", 
                "agree": "88", 
                "channel": "gn", 
                "uid": "1408673611"
            }, 
            {
                "status": "M_PASS", 
                "nick": "空空歌", 
                "thread": "", 
                "parent": "", 
                "level": "0", 
                "ip": "182.247.62.212", 
                "area": "云南文山", 
                "mid": "568331E1-B6F73ED4-6189A1AA-868-96F", 
                "against": "128", 
                "vote": "0", 
                "content": "大快人心事，清理天下，按规矩办事，当官就应该为老百姓办事", 
                "usertype": "", 
                "length": "56", 
                "rank": "0", 
                "time": "2015-12-30 09:22:40", 
                "newsid": "comos-fxmxxsr3989257", 
                "config": "client_port=0&area=云南文山&wb_verified=0&wb_screen_name=唱山空&wb_user_id=1636409770&wb_time=1451438561&wb_profile_img=http%3A%2F%2Ftp3.sinaimg.cn%2F1636409770%2F50%2F5596935311%2F1&area=云南文山", 
                "agree": "128", 
                "channel": "gn", 
                "uid": "1636409770"
            }, 
            {
                "status": "M_PASS", 
                "nick": "用户3752285821", 
                "thread": "", 
                "parent": "", 
                "level": "0", 
                "ip": "119.130.249.97", 
                "area": "广东广州", 
                "mid": "5683317F-7782F961-DFA7567D-868-838", 
                "against": "138", 
                "vote": "0", 
                "content": "都自认为彼此彼此嘛！", 
                "usertype": "", 
                "length": "20", 
                "rank": "0", 
                "time": "2015-12-30 09:21:03", 
                "newsid": "comos-fxmxxsr3989257", 
                "config": "client_port=0&area=广东广州&wb_verified=0&wb_screen_name=善读医愚_65671&wb_user_id=3752285821&wb_time=1451438463&wb_profile_img=http%3A%2F%2Ftp2.sinaimg.cn%2F3752285821%2F50%2F0%2F1&area=广东广州", 
                "agree": "138", 
                "channel": "gn", 
                "uid": "3752285821"
            }, 
            {
                "status": "M_PASS", 
                "nick": "xishanqingxue", 
                "thread": "", 
                "parent": "", 
                "level": "0", 
                "ip": "114.243.227.213", 
                "area": "北京", 
                "mid": "5683306E-72F3E3D5-46878C93-868-8C7", 
                "against": "48", 
                "vote": "0", 
                "content": "给机会就赶紧抓住，起码免去牢狱之灾", 
                "usertype": "", 
                "length": "34", 
                "rank": "0", 
                "time": "2015-12-30 09:16:30", 
                "newsid": "comos-fxmxxsr3989257", 
                "config": "client_port=0&area=北京&wb_verified=0&wb_screen_name=羊头羊脑_pzp&wb_user_id=1183288467&wb_time=1451438190&wb_profile_img=http%3A%2F%2Ftp4.sinaimg.cn%2F1183288467%2F50%2F5598451591%2F1&area=北京", 
                "agree": "48", 
                "channel": "gn", 
                "uid": "1183288467"
            }, 
            {
                "status": "M_PASS", 
                "nick": "用户fvg7yochhq", 
                "thread": "", 
                "parent": "", 
                "level": "0", 
                "ip": "175.21.115.146", 
                "area": "吉林四平", 
                "mid": "56832E02-AF157392-DAE71516-868-9CF", 
                "against": "10", 
                "vote": "0", 
                "content": "交代与持枪反击量刑有何区别？", 
                "usertype": "", 
                "length": "28", 
                "rank": "0", 
                "time": "2015-12-30 09:06:09", 
                "newsid": "comos-fxmxxsr3989257", 
                "config": "client_port=0&area=吉林四平&wb_verified=0&wb_screen_name=用户fvg7yochhq&wb_user_id=3672577302&wb_time=1451437570&wb_profile_img=http%3A%2F%2Ftp3.sinaimg.cn%2F3672577302%2F50%2F0%2F1&area=吉林四平", 
                "agree": "10", 
                "channel": "gn", 
                "uid": "3672577302"
            }, 
            {
                "status": "M_PASS", 
                "nick": "全民健康", 
                "thread": "", 
                "parent": "", 
                "level": "0", 
                "ip": "182.112.51.246", 
                "area": "河南开封", 
                "mid": "56832DBA-B67033F6-51B88287-868-807", 
                "against": "60", 
                "vote": "0", 
                "content": "从标题看是不是可以这样理解，每一个官员的贪腐行为组织上是知道的。", 
                "usertype": "", 
                "length": "64", 
                "rank": "0", 
                "time": "2015-12-30 09:04:58", 
                "newsid": "comos-fxmxxsr3989257", 
                "config": "client_port=0&area=河南开封&wb_verified=0&wb_screen_name=河南全民健康&wb_user_id=1371046535&wb_time=1451437498&wb_profile_img=http%3A%2F%2Ftp4.sinaimg.cn%2F1371046535%2F50%2F0%2F1&area=河南开封", 
                "agree": "60", 
                "channel": "gn", 
                "uid": "1371046535"
            }, 
            {
                "status": "M_PASS", 
                "nick": "顺德老潘", 
                "thread": "", 
                "parent": "", 
                "level": "0", 
                "ip": "61.142.131.119", 
                "area": "广东佛山", 
                "mid": "56832BEA-3D8E8377-9A41407E-868-82E", 
                "against": "19", 
                "vote": "0", 
                "content": "问题严重，他珍惜机会，交代了又如何？[偷笑]", 
                "usertype": "", 
                "length": "42", 
                "rank": "0", 
                "time": "2015-12-30 08:57:13", 
                "newsid": "comos-fxmxxsr3989257", 
                "config": "client_port=0&area=广东佛山&wb_verified=0&wb_screen_name=顺德老潘&wb_user_id=2587967614&wb_time=1451437034&wb_profile_img=http%3A%2F%2Ftp3.sinaimg.cn%2F2587967614%2F50%2F5738286215%2F1&area=广东佛山", 
                "agree": "19", 
                "channel": "gn", 
                "uid": "2587967614"
            }, 
            {
                "status": "M_PASS", 
                "nick": "LIUZIQI", 
                "thread": "", 
                "parent": "", 
                "level": "0", 
                "ip": "113.225.55.205", 
                "area": "辽宁沈阳", 
                "mid": "56832B45-71E137CD-75FD156D-868-81C", 
                "against": "8", 
                "vote": "0", 
                "content": "自己向组织主动说清楚，可以降低办案成本按着政策也可以适当从宽.被动被查出问题严重的要坚决从重处罚.", 
                "usertype": "", 
                "length": "96", 
                "rank": "0", 
                "time": "2015-12-30 08:54:28", 
                "newsid": "comos-fxmxxsr3989257", 
                "config": "client_port=0&area=辽宁沈阳&wb_verified=0&wb_screen_name=ZIQIDEXUANZHE&wb_user_id=1979520365&wb_time=1451436869&wb_profile_img=http%3A%2F%2Ftp2.sinaimg.cn%2F1979520365%2F50%2F0%2F1&area=辽宁沈阳", 
                "agree": "8", 
                "channel": "gn", 
                "uid": "1979520365"
            }, 
            {
                "status": "M_PASS", 
                "nick": "信天翁", 
                "thread": "", 
                "parent": "", 
                "level": "0", 
                "ip": "60.10.71.233", 
                "area": "河北廊坊", 
                "mid": "56831DF7-3C0A47E9-747DE3CE-868-7E0", 
                "against": "7", 
                "vote": "0", 
                "content": "可惜此生错投.", 
                "usertype": "", 
                "length": "13", 
                "rank": "0", 
                "time": "2015-12-30 07:57:42", 
                "newsid": "comos-fxmxxsr3989257", 
                "config": "client_port=0&area=河北廊坊&wb_verified=0&wb_screen_name=浪迹天涯信天翁&wb_user_id=1954407374&wb_time=1451433463&wb_profile_img=http%3A%2F%2Ftp3.sinaimg.cn%2F1954407374%2F50%2F0%2F1&area=河北廊坊", 
                "agree": "7", 
                "channel": "gn", 
                "uid": "1954407374"
            }, 
            {
                "status": "M_PASS", 
                "nick": "老臭的悲伤", 
                "thread": "", 
                "parent": "", 
                "level": "0", 
                "ip": "117.136.5.72", 
                "area": "辽宁沈阳", 
                "mid": "5682D4E3-75880548-AE93F075-868-85A", 
                "against": "156", 
                "vote": "0", 
                "content": "依法治国", 
                "usertype": "wap", 
                "length": "8", 
                "rank": "0", 
                "time": "2015-12-30 02:45:54", 
                "newsid": "comos-fxmxxsr3989257", 
                "config": "OS_TYPE=14&SOFT_TYPE=Build/KTU84P) Chrome/33.0.0.0 Safari/537.36&area=辽宁沈阳&wb_verified=0&wb_screen_name=老臭的悲伤&wb_user_id=2928930933&wb_time=1451414755&wb_profile_img=http%3A%2F%2Ftp2.sinaimg.cn%2F2928930933%2F50%2F5681273973%2F0&area=辽宁沈阳", 
                "agree": "156", 
                "channel": "gn", 
                "uid": "2928930933"
            }, 
            {
                "status": "M_PASS", 
                "nick": "合金橘子", 
                "thread": "", 
                "parent": "", 
                "level": "0", 
                "ip": "125.68.70.158", 
                "area": "四川德阳", 
                "mid": "56829E77-7D44469E-E821B9B0-868-8AB", 
                "against": "33", 
                "vote": "0", 
                "content": "相由心生   这话管用", 
                "usertype": "client", 
                "length": "19", 
                "rank": "0", 
                "time": "2015-12-29 22:53:43", 
                "newsid": "comos-fxmxxsr3989257", 
                "config": "&from=palmnews&wb_verified=0&wb_screen_name=合金橘子&wb_user_id=3894524336&wb_time=1451400823&wb_profile_img=http%3A%2F%2Ftp1.sinaimg.cn%2F3894524336%2F50%2F5723022271%2F1&area=四川德阳", 
                "agree": "33", 
                "channel": "gn", 
                "uid": "3894524336"
            }, 
            {
                "status": "M_PASS", 
                "nick": "塔", 
                "thread": "", 
                "parent": "", 
                "level": "0", 
                "ip": "222.81.38.229", 
                "area": "新疆石河子", 
                "mid": "56829B03-DE5126E5-4FC0488E-868-799", 
                "against": "78", 
                "vote": "0", 
                "content": "说了实话就没罪吗", 
                "usertype": "wap", 
                "length": "16", 
                "rank": "0", 
                "time": "2015-12-29 22:38:59", 
                "newsid": "comos-fxmxxsr3989257", 
                "config": "from=ucweb&OS_TYPE=14&SOFT_TYPE=Build/Che1-CL10) UCBrowser/10.8.5.689 U3/0.8.0 Safari/534.30&area=新疆石河子&area=新疆石河子", 
                "agree": "78", 
                "channel": "gn", 
                "uid": "1338001550"
            }, 
            {
                "status": "M_PASS", 
                "nick": "素烧小丸子", 
                "thread": "", 
                "parent": "", 
                "level": "0", 
                "ip": "180.104.32.240", 
                "area": "江苏徐州", 
                "mid": "568299BA-B46820F0-AF8ABEDB-868-7F6", 
                "against": "18", 
                "vote": "0", 
                "content": "还想报绞性心理，最后只是死路一条。", 
                "usertype": "client", 
                "length": "34", 
                "rank": "0", 
                "time": "2015-12-29 22:33:30", 
                "newsid": "comos-fxmxxsr3989257", 
                "config": "OS_TYPE=14&OS_LANG=zh&SOFT_TYPE=SinaNews_v481&LATITUDE=34.212421&LONGITUDE=117.14018&client_ip=180.104.32.240&port=26159&from=palmnews&wb_verified=0&wb_screen_name=素烧小丸子&wb_user_id=2945105627&wb_time=1451399610&wb_profile_img=http%3A%2F%2Ftp4.sinaimg.cn%2F2945105627%2F50%2F40076688297%2F1&area=江苏徐州", 
                "agree": "18", 
                "channel": "gn", 
                "uid": "2945105627"
            }, 
            {
                "status": "M_PASS", 
                "nick": "用户5736548655", 
                "thread": "", 
                "parent": "", 
                "level": "0", 
                "ip": "120.210.182.209", 
                "area": "安徽滁州", 
                "mid": "568296A7-78D2B6D1-155ECC92F-868-8F0", 
                "against": "62", 
                "vote": "0", 
                "content": "听起来好像有哪位官员说实话似的！", 
                "usertype": "client", 
                "length": "32", 
                "rank": "0", 
                "time": "2015-12-29 22:20:23", 
                "newsid": "comos-fxmxxsr3989257", 
                "config": "&from=palmnews&wb_verified=0&wb_screen_name=我是吴守仙&wb_user_id=5736548655&wb_time=1451398823&wb_profile_img=http%3A%2F%2Ftp4.sinaimg.cn%2F5736548655%2F50%2F5740556829%2F1&area=安徽滁州", 
                "agree": "62", 
                "channel": "gn", 
                "uid": "5736548655"
            }, 
            {
                "status": "M_PASS", 
                "nick": "biaopieany", 
                "thread": "", 
                "parent": "", 
                "level": "0", 
                "ip": "183.204.33.144", 
                "area": "河南信阳", 
                "mid": "568295CE-B7CC2190-132CC1769-868-91E", 
                "against": "59", 
                "vote": "0", 
                "content": "出了这么多臭虫，以前怎么没发现？请解释。", 
                "usertype": "wap", 
                "length": "40", 
                "rank": "0", 
                "time": "2015-12-29 22:16:46", 
                "newsid": "comos-fxmxxsr3989257", 
                "config": "OS_TYPE=14&SOFT_TYPE=Build/KTU84P) Chrome/33.0.0.0 Safari/537.36&area=河南信阳&area=河南信阳", 
                "agree": "59", 
                "channel": "gn", 
                "uid": "5147203433"
            }, 
            {
                "status": "M_PASS", 
                "nick": "美丽洁洁1", 
                "thread": "", 
                "parent": "", 
                "level": "0", 
                "ip": "101.254.209.14", 
                "area": "北京", 
                "mid": "56829359-65FED10E-D2DB0A64-868-8E7", 
                "against": "33", 
                "vote": "0", 
                "content": "其实，证监会的那位抓了放，是不是也是给机会？", 
                "usertype": "client", 
                "length": "44", 
                "rank": "0", 
                "time": "2015-12-29 22:06:17", 
                "newsid": "comos-fxmxxsr3989257", 
                "config": "OS_TYPE=14&OS_LANG=zh&SOFT_TYPE=SinaNews_v491&LATITUDE=4.9E-324&LONGITUDE=4.9E-324&client_ip=101.254.209.14&port=12422&from=palmnews&wb_verified=0&wb_screen_name=美丽洁洁1&wb_user_id=3537570404&wb_time=1451397977&wb_profile_img=http%3A%2F%2Ftp1.sinaimg.cn%2F3537570404%2F50%2F0%2F1&area=北京", 
                "agree": "33", 
                "channel": "gn", 
                "uid": "3537570404"
            }, 
            {
                "status": "M_PASS", 
                "nick": "bobby", 
                "thread": "", 
                "parent": "", 
                "level": "0", 
                "ip": "101.191.19.167", 
                "area": "澳大利亚新南威尔士", 
                "mid": "56828794-65BF13A7-5ACFAD9D-868-8F9", 
                "against": "81", 
                "vote": "0", 
                "content": "实在不明白每一只老虎都可以折腾十几年，上下级都能充耳不闻，听之任之，到最后还给他们机会？", 
                "usertype": "client", 
                "length": "88", 
                "rank": "0", 
                "time": "2015-12-29 21:16:04", 
                "newsid": "comos-fxmxxsr3989257", 
                "config": "&from=palmnews&wb_verified=0&wb_screen_name=健忘的独乐者&wb_user_id=1523559837&wb_time=1451394964&wb_profile_img=http%3A%2F%2Ftp2.sinaimg.cn%2F1523559837%2F50%2F40056420912%2F1&area=澳大利亚新南威尔士", 
                "agree": "81", 
                "channel": "gn", 
                "uid": "1523559837"
            }, 
            {
                "status": "M_PASS", 
                "nick": "zjyyywq", 
                "thread": "", 
                "parent": "", 
                "level": "0", 
                "ip": "211.138.199.175", 
                "area": "江苏南京", 
                "mid": "56827FC9-D38AC7AF-467553C9-868-8A3", 
                "against": "157", 
                "vote": "0", 
                "content": "很好的", 
                "usertype": "client", 
                "length": "6", 
                "rank": "0", 
                "time": "2015-12-29 20:42:49", 
                "newsid": "comos-fxmxxsr3989257", 
                "config": "&from=palmnews&wb_verified=0&wb_screen_name=指间有缘&wb_user_id=1182094281&wb_time=1451392969&wb_profile_img=http%3A%2F%2Ftp2.sinaimg.cn%2F1182094281%2F50%2F0%2F1&area=江苏南京", 
                "agree": "157", 
                "channel": "gn", 
                "uid": "1182094281"
            }, 
            {
                "status": "M_PASS", 
                "nick": "用户1911756383", 
                "thread": "", 
                "parent": "", 
                "level": "0", 
                "ip": "178.197.236.22", 
                "area": "瑞士", 
                "mid": "56827E68-B2C5EC16-71F3165F-868-815", 
                "against": "41", 
                "vote": "0", 
                "content": "如果说了实话就不处理吗？", 
                "usertype": "client", 
                "length": "24", 
                "rank": "0", 
                "time": "2015-12-29 20:36:56", 
                "newsid": "comos-fxmxxsr3989257", 
                "config": "&from=palmnews&wb_verified=0&wb_screen_name=挺大大反腐&wb_user_id=1911756383&wb_time=1451392616&wb_profile_img=http%3A%2F%2Ftp4.sinaimg.cn%2F1911756383%2F50%2F40013636113%2F1&area=瑞士", 
                "agree": "41", 
                "channel": "gn", 
                "uid": "1911756383"
            }
        ], 
        "cmntlist_wb_verified": [], 
        "news": {
            "status": "N_NORMAL", 
            "anonymous": "A_DEFAULT", 
            "title": "白雪山被曝曾有一个交待的机会 媒体：他未珍惜", 
            "default": "M_CHECK", 
            "channel": "gn", 
            "show": "M_PASS,M_NICE", 
            "tagalias": "", 
            "topic": "", 
            "column": "comos-56044", 
            "script": "", 
            "base": "0", 
            "url": "http://news.sina.com.cn/c/nd/2015-12-29/doc-ifxmxxsr3989257.shtml", 
            "groups": "", 
            "time": "2015-12-29 20:30:32", 
            "newsid": "comos-fxmxxsr3989257", 
            "countmode": "C_HIDE,C_QREPLY,C_SHOW", 
            "config": "url_wap=http%3A%2F%2Fnews.sina.cn%2Fgn%2F2015-12-29%2Fdetail-ifxmxxsr3989257.d.html", 
            "subnum": "0"
        }, 
        "grouplist": [], 
        "hot_list": [
            {
                "status": "M_PASS", 
                "nick": "帅且幽默", 
                "thread": "", 
                "parent": "", 
                "level": "0", 
                "ip": "171.220.17.8", 
                "area": "四川成都", 
                "mid": "5683406C-ABDC1108-8F7FB57C-868-86D", 
                "against": "213", 
                "vote": "0", 
                "content": "说了实话就不用追究犯罪行为啦？", 
                "usertype": "client", 
                "length": "30", 
                "rank": "0", 
                "time": "2015-12-30 10:24:44", 
                "newsid": "comos-fxmxxsr3989257", 
                "config": "&from=palmnews&wb_verified=0&wb_screen_name=帅且幽默&wb_user_id=2407511420&wb_time=1451442284&wb_profile_img=http%3A%2F%2Ftp1.sinaimg.cn%2F2407511420%2F50%2F5728468872%2F1&area=四川成都", 
                "agree": "213", 
                "channel": "gn", 
                "uid": "2407511420"
            }, 
            {
                "status": "M_PASS", 
                "nick": "用户5806208808", 
                "thread": "", 
                "parent": "", 
                "level": "0", 
                "ip": "218.87.161.178", 
                "area": "江西吉安", 
                "mid": "56834DF3-DA57A1B2-15A13B728-868-8F2", 
                "against": "169", 
                "vote": "0", 
                "content": "媒体咋啥都晓得，特别是在事后？！！！", 
                "usertype": "", 
                "length": "36", 
                "rank": "0", 
                "time": "2015-12-30 11:22:27", 
                "newsid": "comos-fxmxxsr3989257", 
                "config": "client_port=0&area=江西吉安&area=江西吉安", 
                "agree": "169", 
                "channel": "gn", 
                "uid": "5806208808"
            }, 
            {
                "status": "M_PASS", 
                "nick": "愿如梁上燕_叹花不解言", 
                "thread": "568295CE-B7CC2190-132CC1769-868-91E", 
                "parent": "568295CE-B7CC2190-132CC1769-868-91E", 
                "level": "1", 
                "ip": "14.134.205.232", 
                "area": "宁夏固原", 
                "mid": "5683470A-E86CDE8-68ECA043-868-97D", 
                "against": "111", 
                "vote": "0", 
                "content": "装聋作哑，上梁不正下梁歪。", 
                "usertype": "", 
                "length": "26", 
                "rank": "0", 
                "time": "2015-12-30 10:52:57", 
                "newsid": "comos-fxmxxsr3989257", 
                "config": "client_port=0&area=宁夏固原&wb_verified=0&wb_screen_name=愿如梁上燕_叹花不解言&wb_user_id=1760337987&wb_time=1451443978&wb_profile_img=http%3A%2F%2Ftp4.sinaimg.cn%2F1760337987%2F50%2F5679964208%2F0&area=宁夏固原", 
                "agree": "111", 
                "channel": "gn", 
                "uid": "1760337987"
            }, 
            {
                "status": "M_PASS", 
                "nick": "用户1909338723", 
                "thread": "", 
                "parent": "", 
                "level": "0", 
                "ip": "120.36.149.49", 
                "area": "福建厦门", 
                "mid": "56834D7E-78249531-71CE3263-868-83C", 
                "against": "78", 
                "vote": "0", 
                "content": "没办法！胜者王败者寇，顺应潮流", 
                "usertype": "", 
                "length": "30", 
                "rank": "0", 
                "time": "2015-12-30 11:20:30", 
                "newsid": "comos-fxmxxsr3989257", 
                "config": "client_port=0&area=福建厦门&wb_verified=0&wb_screen_name=微博云中鹏&wb_user_id=1909338723&wb_time=1451445630&wb_profile_img=http%3A%2F%2Ftp4.sinaimg.cn%2F1909338723%2F50%2F5606316287%2F1&area=福建厦门", 
                "agree": "78", 
                "channel": "gn", 
                "uid": "1909338723"
            }, 
            {
                "status": "M_PASS", 
                "nick": "愿如梁上燕_叹花不解言", 
                "thread": "56829B03-DE5126E5-4FC0488E-868-799", 
                "parent": "56829B03-DE5126E5-4FC0488E-868-799", 
                "level": "1", 
                "ip": "14.134.205.232", 
                "area": "宁夏固原", 
                "mid": "568346D5-E86CDE8-68ECA043-868-8CE", 
                "against": "63", 
                "vote": "0", 
                "content": "至少是立功表现，减轻处罚。", 
                "usertype": "", 
                "length": "26", 
                "rank": "0", 
                "time": "2015-12-30 10:52:05", 
                "newsid": "comos-fxmxxsr3989257", 
                "config": "client_port=0&area=宁夏固原&wb_verified=0&wb_screen_name=愿如梁上燕_叹花不解言&wb_user_id=1760337987&wb_time=1451443925&wb_profile_img=http%3A%2F%2Ftp4.sinaimg.cn%2F1760337987%2F50%2F5679964208%2F0&area=宁夏固原", 
                "agree": "63", 
                "channel": "gn", 
                "uid": "1760337987"
            }, 
            {
                "status": "M_PASS", 
                "nick": "敌敌危", 
                "thread": "", 
                "parent": "", 
                "level": "0", 
                "ip": "14.152.68.210", 
                "area": "广东广州", 
                "mid": "568368C1-E9844D2-551D5556-868-8F4", 
                "against": "44", 
                "vote": "0", 
                "content": "“可杀不可辱”，共产党员么，绝不苟且偷生～～", 
                "usertype": "wap", 
                "length": "44", 
                "rank": "0", 
                "time": "2015-12-30 13:16:48", 
                "newsid": "comos-fxmxxsr3989257", 
                "config": "from=ucweb&OS_TYPE=13&SOFT_TYPE=UCBrowser/10.7.1.655&area=广东广州&wb_verified=0&wb_screen_name=敌敌危&wb_user_id=1427985750&wb_time=1451452609&wb_profile_img=http%3A%2F%2Ftp3.sinaimg.cn%2F1427985750%2F50%2F5608893412%2F1&area=广东广州", 
                "agree": "44", 
                "channel": "gn", 
                "uid": "1427985750"
            }, 
            {
                "status": "M_PASS", 
                "nick": "lyhgeomag", 
                "thread": "", 
                "parent": "", 
                "level": "0", 
                "ip": "218.247.1.1", 
                "area": "北京", 
                "mid": "56836A13-DAF70101-57144268-868-91A", 
                "against": "55", 
                "vote": "0", 
                "content": "aaa", 
                "usertype": "", 
                "length": "3", 
                "rank": "0", 
                "time": "2015-12-30 13:22:27", 
                "newsid": "comos-fxmxxsr3989257", 
                "config": "client_port=0&area=北京&area=北京", 
                "agree": "55", 
                "channel": "gn", 
                "uid": "1460945512"
            }, 
            {
                "status": "M_PASS", 
                "nick": "蓝色影子", 
                "thread": "", 
                "parent": "", 
                "level": "0", 
                "ip": "117.177.240.39", 
                "area": "四川内江", 
                "mid": "5683664C-75B1F027-4A6AD4C7-868-990", 
                "against": "34", 
                "vote": "0", 
                "content": "天啦,他要珍惜了是不是就官复原职?", 
                "usertype": "", 
                "length": "32", 
                "rank": "0", 
                "time": "2015-12-30 13:06:20", 
                "newsid": "comos-fxmxxsr3989257", 
                "config": "client_port=0&area=四川内江&wb_verified=0&wb_screen_name=蓝色影子w&wb_user_id=1248515271&wb_time=1451451980&wb_profile_img=http%3A%2F%2Ftp4.sinaimg.cn%2F1248515271%2F50%2F0%2F1&area=四川内江", 
                "agree": "34", 
                "channel": "gn", 
                "uid": "1248515271"
            }, 
            {
                "status": "M_PASS", 
                "nick": "淡泊明志", 
                "thread": "", 
                "parent": "", 
                "level": "0", 
                "ip": "118.72.71.114", 
                "area": "山西大同", 
                "mid": "56835103-76484772-9F182FB1-868-839", 
                "against": "19", 
                "vote": "0", 
                "content": "树倒猴孙散，墙倒众人推。", 
                "usertype": "", 
                "length": "24", 
                "rank": "0", 
                "time": "2015-12-30 11:35:30", 
                "newsid": "comos-fxmxxsr3989257", 
                "config": "client_port=0&area=山西大同&wb_verified=0&wb_screen_name=GM不是请客吃饭&wb_user_id=2669162417&wb_time=1451446531&wb_profile_img=http%3A%2F%2Ftp2.sinaimg.cn%2F2669162417%2F50%2F0%2F1&area=山西大同", 
                "agree": "19", 
                "channel": "gn", 
                "uid": "2669162417"
            }, 
            {
                "status": "M_PASS", 
                "nick": "妩媚没什么大不了的", 
                "thread": "", 
                "parent": "", 
                "level": "0", 
                "ip": "106.45.192.80", 
                "area": "宁夏吴忠", 
                "mid": "56834709-6A2DC050-139B5C02A-868-96D", 
                "against": "16", 
                "vote": "0", 
                "content": "太轻了！直接抓去枪毙，压在人民群众头顶上的蛀虫！何必惋惜！中国不差千里马！", 
                "usertype": "", 
                "length": "74", 
                "rank": "0", 
                "time": "2015-12-30 10:52:56", 
                "newsid": "comos-fxmxxsr3989257", 
                "config": "client_port=0&area=宁夏吴忠&wb_verified=0&wb_screen_name=妩媚没什么大不了的&wb_user_id=5263179818&wb_time=1451443977&wb_profile_img=http%3A%2F%2Ftp3.sinaimg.cn%2F5263179818%2F50%2F5703546401%2F1&area=宁夏吴忠", 
                "agree": "16", 
                "channel": "gn", 
                "uid": "5263179818"
            }
        ]
    }
}